killstats/__init__.py
killstats/admin.py
killstats/app_settings.py
killstats/apps.py
killstats/auth_hooks.py
killstats/constants.py
killstats/decorators.py
killstats/errors.py
killstats/forms.py
killstats/hooks.py
killstats/providers.py
killstats/signals.py
killstats/tasks.py
killstats/urls.py
killstats/views.py
killstats/api/__init__.py
killstats/api/account_manager.py
killstats/api/helpers.py
killstats/api/schema.py
killstats/api/killstats/__init__.py
killstats/api/killstats/admin.py
killstats/api/killstats/api_helper.py
killstats/api/killstats/killboard.py
killstats/api/killstats/stats.py
killstats/docs/explanation.md
killstats/docs/img/killstats1.png
killstats/docs/img/killstats2.png
killstats/docs/img/killstats3.png
killstats/helpers/killmail.py
killstats/locale/__init__.py
killstats/locale/django.pot
killstats/locale/cs_CZ/LC_MESSAGES/django.po
killstats/locale/de/LC_MESSAGES/django.mo
killstats/locale/de/LC_MESSAGES/django.po
killstats/locale/es/LC_MESSAGES/django.po
killstats/locale/fr_FR/LC_MESSAGES/django.po
killstats/locale/it_IT/LC_MESSAGES/django.po
killstats/locale/ja/LC_MESSAGES/django.po
killstats/locale/ko_KR/LC_MESSAGES/django.po
killstats/locale/nl_NL/LC_MESSAGES/django.po
killstats/locale/pl_PL/LC_MESSAGES/django.po
killstats/locale/ru/LC_MESSAGES/django.po
killstats/locale/sk/LC_MESSAGES/django.po
killstats/locale/uk/LC_MESSAGES/django.po
killstats/locale/zh_Hans/LC_MESSAGES/django.po
killstats/management/commands/migrate_old_killmails.py
killstats/managers/__init__.py
killstats/managers/killboard_manager.py
killstats/managers/killboardaudit_manager.py
killstats/migrations/0001_initial.py
killstats/migrations/0002_rename_killstatsaudit_corporationsaudit_and_more.py
killstats/migrations/0003_attacker_remove_killmail_attackers_and_more.py
killstats/migrations/0004_migrate_attacker.py
killstats/migrations/0005_alter_general_options.py
killstats/migrations/0006_alter_attacker_weapon_type_id_and_more.py
killstats/migrations/__init__.py
aa_killstats-1.0.3.dist-info/METADATA
aa_killstats-1.0.3.dist-info/WHEEL
aa_killstats-1.0.3.dist-info/licenses/LICENSE
aa_killstats-1.0.3.dist-info/RECORD
