Metadata-Version: 2.4
Name: aa-killstats
Version: 1.0.3
Summary: Killboard Stats shows Hall of Shame/Fame, Kills, Top Kills,Loss,etc.
Project-URL: Changelog, https://github.com/Geuthur/aa-killstats/blob/master/CHANGELOG.md
Project-URL: Documentation, https://github.com/Geuthur/aa-killstats/blob/master/README.md
Project-URL: Donations, https://ko-fi.com/Geuthur
Project-URL: Homepage, https://github.com/Geuthur/aa-killstats
Project-URL: Source, https://github.com/Geuthur/aa-killstats
Project-URL: Tracker, https://github.com/Geuthur/aa-killstats/issues
Author-email: Geuthur <devgeuthur@gmail.com>
License:                     GNU GENERAL PUBLIC LICENSE
License-File: LICENSE
Classifier: Environment :: Web Environment
Classifier: Framework :: Django
Classifier: Framework :: Django :: 4.2
Classifier: Intended Audience :: Developers
Classifier: License :: OSI Approved :: GNU General Public License v3 (GPLv3)
Classifier: Operating System :: OS Independent
Classifier: Programming Language :: Python
Classifier: Programming Language :: Python :: 3 :: Only
Classifier: Programming Language :: Python :: 3.10
Classifier: Programming Language :: Python :: 3.11
Classifier: Programming Language :: Python :: 3.12
Classifier: Programming Language :: Python :: 3.13
Classifier: Programming Language :: Python :: 3.14
Classifier: Topic :: Internet :: WWW/HTTP
Classifier: Topic :: Internet :: WWW/HTTP :: Dynamic Content
Requires-Python: >=3.10
Requires-Dist: allianceauth-app-utils>=1.3
Requires-Dist: allianceauth<5,>=4.10
Requires-Dist: dacite
Requires-Dist: django-esi<9,>=8
Requires-Dist: django-eveuniverse>=1.6
Requires-Dist: django-ninja
Provides-Extra: tests-allianceauth-latest
Requires-Dist: coverage; extra == 'tests-allianceauth-latest'
Requires-Dist: factory-boy; extra == 'tests-allianceauth-latest'
